{"name":"Icogram 2026-04-08 15:27","version":"1.2","width":8000,"height":8000,"backgroundColor":"#FFFFFF","backgroundOpacity":"1.0","icogramContent":[{"id":68,"x":8,"y":284,"width":96,"height":80,"type":"f3","iconCode":"figure3001","figure":{"type":"cube","pattern":{"name":"color:#3399CC"},"width":64,"height":64,"widthLeft":64},"colorMapping":{}},{"id":11,"x":40,"y":348,"width":96,"height":112,"type":"f3","iconCode":"figure3001","figure":{"type":"cube","pattern":{"name":"color:#3399CC"},"width":64,"height":64,"widthLeft":32},"colorMapping":{}},{"id":10,"x":104,"y":348,"width":64,"height":96,"type":"f3","iconCode":"figure3001","figure":{"type":"cube","pattern":{"name":"color:#3399CC"},"width":64,"height":64,"widthLeft":32},"colorMapping":{}},{"id":20,"iconCode":"chart127","x":104,"y":284,"width":64,"height":40,"src":"charts/stairs-07.svg","colorMapping":{"#3399CC":"#3399CC"}},{"id":18,"x":72,"y":364,"width":64,"height":80,"type":"f3","iconCode":"chart002","figure":{"type":"cube","pattern":{"name":"color:#3399CC"},"width":64,"height":48,"widthLeft":32},"colorMapping":{}},{"id":19,"x":104,"y":380,"width":64,"height":64,"type":"f3","iconCode":"chart003","figure":{"type":"cube","pattern":{"name":"color:#3399CC"},"width":64,"height":64},"colorMapping":{}},{"id":12,"x":136,"y":348,"width":64,"height":96,"type":"f3","iconCode":"figure3001","figure":{"type":"cube","pattern":{"name":"color:#3399CC"},"width":64,"height":64,"widthLeft":32},"colorMapping":{}},{"id":9,"x":40,"y":444,"width":576,"height":320,"type":"f3","iconCode":"figure3001","figure":{"type":"cube","pattern":{"name":"color:#3399CC"},"width":64,"height":64,"widthLeft":32},"colorMapping":{}},{"id":16,"iconCode":"chart126","x":104,"y":348,"width":64,"height":48,"src":"charts/stairs-06.svg","colorMapping":{"#3399CC":"#3399CC"}},{"id":17,"iconCode":"chart126","x":72,"y":316,"width":64,"height":48,"src":"charts/stairs-06.svg","colorMapping":{"#3399CC":"#3399CC"}},{"id":21,"iconCode":"chart127","x":136,"y":284,"width":64,"height":40,"src":"charts/stairs-07.svg","colorMapping":{"#3399CC":"#3399CC"}},{"id":29,"iconCode":"img807","x":40,"y":420,"width":32,"height":48,"src":"office/revolving-doors.svg","scale":"2.00","colorMapping":{"#999999":"#999999","#3399CC":"#3399CC"}},{"id":35,"x":200,"y":396,"width":64,"height":112,"type":"f3","iconCode":"chart003","figure":{"type":"cube","pattern":{"name":"color:#3399CC"},"width":64,"height":64,"widthLeft":32},"colorMapping":{}},{"id":36,"x":232,"y":412,"width":64,"height":96,"type":"f3","iconCode":"chart003","figure":{"type":"cube","pattern":{"name":"color:#3399CC"},"width":64,"height":64,"widthLeft":32},"colorMapping":{}},{"id":37,"x":168,"y":412,"width":64,"height":64,"type":"f3","iconCode":"chart003","figure":{"type":"cube","pattern":{"name":"color:#3399CC"},"width":64,"height":64},"colorMapping":{}},{"id":40,"iconCode":"chart127","x":168,"y":380,"width":64,"height":40,"src":"charts/stairs-07.svg","colorMapping":{"#3399CC":"#3399CC"}},{"id":41,"x":200,"y":428,"width":64,"height":80,"type":"f3","iconCode":"chart003","figure":{"type":"cube","pattern":{"name":"color:#3399CC"},"width":64,"height":64,"widthLeft":32},"colorMapping":{}},{"id":42,"iconCode":"chart127","x":200,"y":380,"width":64,"height":40,"src":"charts/stairs-07.svg","colorMapping":{"#3399CC":"#3399CC"}},{"id":43,"x":232,"y":444,"width":96,"height":112,"type":"f3","iconCode":"chart003","figure":{"type":"cube","pattern":{"name":"color:#3399CC"},"width":64,"height":64,"widthLeft":32},"colorMapping":{}},{"id":44,"iconCode":"chart126","x":232,"y":348,"width":64,"height":48,"src":"charts/stairs-06.svg","colorMapping":{"#3399CC":"#3399CC"}},{"id":48,"iconCode":"img412","x":264,"y":284,"width":16,"height":32,"src":"rooms/door-01.svg","scale":"2.00","originalScale":0.1,"colorMapping":{"#BAA794":"#BAA794","#762C07":"#762C07","#825012":"#825012","#999999":"#999999"}},{"id":49,"iconCode":"img412","x":360,"y":236,"width":16,"height":32,"src":"rooms/door-01.svg","scale":"2.00","originalScale":0.1,"colorMapping":{"#BAA794":"#BAA794","#762C07":"#762C07","#825012":"#825012","#999999":"#999999"}},{"id":50,"iconCode":"img412","x":456,"y":188,"width":16,"height":32,"src":"rooms/door-01.svg","scale":"2.00","originalScale":0.1,"colorMapping":{"#BAA794":"#BAA794","#762C07":"#762C07","#825012":"#825012","#999999":"#999999"}},{"id":51,"iconCode":"img412","x":296,"y":300,"width":16,"height":32,"src":"rooms/door-01.svg","scale":"2.00","originalScale":0.1,"colorMapping":{"#BAA794":"#BAA794","#762C07":"#762C07","#825012":"#825012","#999999":"#999999"}},{"id":52,"iconCode":"img412","x":392,"y":252,"width":16,"height":32,"src":"rooms/door-01.svg","scale":"2.00","originalScale":0.1,"colorMapping":{"#BAA794":"#BAA794","#762C07":"#762C07","#825012":"#825012","#999999":"#999999"}},{"id":53,"iconCode":"img412","x":488,"y":204,"width":16,"height":32,"src":"rooms/door-01.svg","scale":"2.00","originalScale":0.1,"colorMapping":{"#BAA794":"#BAA794","#762C07":"#762C07","#825012":"#825012","#999999":"#999999"}},{"id":64,"iconCode":"img3700","x":584,"y":140,"width":16,"height":32,"src":"office/fire-door-02.svg","scale":"2.00","originalScale":0.1,"colorMapping":{"#E5E5E5":"#E5E5E5","#CC291F":"#CC291F","#999999":"#999999"}},{"id":22,"x":200,"y":300,"width":416,"height":240,"type":"f3","iconCode":"chart003","figure":{"type":"cube","pattern":{"name":"color:#3399CC"},"width":64,"height":64,"widthLeft":32},"colorMapping":{}},{"id":54,"iconCode":"img412","x":296,"y":236,"width":16,"height":32,"src":"rooms/door-01.svg","scale":"2.00","originalScale":0.1,"colorMapping":{"#BAA794":"#BAA794","#762C07":"#762C07","#825012":"#825012","#999999":"#999999"}},{"id":55,"iconCode":"img412","x":264,"y":220,"width":16,"height":32,"src":"rooms/door-01.svg","scale":"2.00","originalScale":0.1,"colorMapping":{"#BAA794":"#BAA794","#762C07":"#762C07","#825012":"#825012","#999999":"#999999"}},{"id":57,"iconCode":"img412","x":360,"y":172,"width":16,"height":32,"src":"rooms/door-01.svg","scale":"2.00","originalScale":0.1,"colorMapping":{"#BAA794":"#BAA794","#762C07":"#762C07","#825012":"#825012","#999999":"#999999"}},{"id":58,"iconCode":"img436","x":392,"y":188,"width":16,"height":32,"src":"rooms/door-11.svg","scale":"2.00","originalScale":0.1,"colorMapping":{"#BAA794":"#BAA794","#762C07":"#762C07","#825012":"#825012","#999999":"#999999"}},{"id":59,"iconCode":"img412","x":456,"y":124,"width":16,"height":32,"src":"rooms/door-01.svg","scale":"2.00","originalScale":0.1,"colorMapping":{"#BAA794":"#BAA794","#762C07":"#762C07","#825012":"#825012","#999999":"#999999"}},{"id":60,"iconCode":"img412","x":488,"y":140,"width":16,"height":32,"src":"rooms/door-01.svg","scale":"2.00","originalScale":0.1,"colorMapping":{"#BAA794":"#BAA794","#762C07":"#762C07","#825012":"#825012","#999999":"#999999"}},{"id":61,"x":360,"y":268,"width":192,"height":112,"type":"f3","iconCode":"chart002","figure":{"type":"cube","pattern":{"name":"color:#3399CC"},"width":64,"height":48,"widthLeft":96},"colorMapping":{}},{"id":62,"iconCode":"img992","x":448,"y":212,"width":2,"height":2,"src":"office/key.svg","scale":12,"originalScale":0.1,"colorMapping":{"#999999":"#539B00"}},{"id":63,"iconCode":"img2738","x":56,"y":396,"width":32,"height":32,"src":"markers/symbol-exit.svg","colorMapping":{"#2D3134":"#2D3134"},"type":"s"},{"id":65,"x":168,"y":300,"width":64,"height":48,"type":"f3","iconCode":"chart002","figure":{"type":"cube","pattern":{"name":"color:#3399CC"},"width":64,"height":48},"colorMapping":{}},{"id":45,"iconCode":"chart126","x":200,"y":316,"width":64,"height":48,"src":"charts/stairs-06.svg","colorMapping":{"#3399CC":"#3399CC"}},{"id":66,"iconCode":"img3700","x":584,"y":76,"width":16,"height":32,"src":"office/fire-door-02.svg","scale":"2.00","originalScale":0.1,"colorMapping":{"#E5E5E5":"#E5E5E5","#CC291F":"#CC291F","#999999":"#999999"}},{"id":67,"iconCode":"img3700","x":8,"y":220,"width":16,"height":32,"src":"office/fire-door-02.svg","scale":"2.00","originalScale":0.1,"colorMapping":{"#E5E5E5":"#E5E5E5","#CC291F":"#CC291F","#999999":"#999999"},"flip":-1},{"id":69,"x":296,"y":428,"width":96,"height":80,"type":"f3","iconCode":"figure3001","figure":{"type":"cube","pattern":{"name":"color:#3399CC"},"width":64,"height":64,"widthLeft":64},"colorMapping":{}},{"id":70,"iconCode":"img3700","x":360,"y":396,"width":16,"height":32,"src":"office/fire-door-02.svg","scale":"2.00","originalScale":0.1,"colorMapping":{"#E5E5E5":"#E5E5E5","#CC291F":"#CC291F","#999999":"#999999"},"flip":-1},{"id":77,"x":672,"y":80,"width":16,"height":16,"type":"f3","iconCode":"chart001","figure":{"type":"cube","pattern":{"name":"color:#3399CC"},"width":32,"height":32,"widthLeft":8},"colorMapping":{}},{"id":78,"iconCode":"img3483","x":690,"y":66,"width":56,"height":24,"src":"text/text01-html.svg","colorMapping":{},"textData":{"rows":8,"originalText":{"ops":[{"insert":"Body text. Body text."},{"insert":"\n"},{"insert":"Body text. Body text."},{"insert":"\n"},{"insert":"Body text. Body text."},{"insert":"\n"}]},"text":{"ops":[{"insert":"Ground\n"}]},"style":{"fontName":"Arial","fontSize":14,"fillColor":"#2D3134","lineHeight":1},"textType":"quill"},"type":"t","scale":0.5},{"id":79,"iconCode":"img2738","x":672,"y":104,"width":32,"height":32,"src":"markers/symbol-exit.svg","colorMapping":{"#2D3134":"#2D3134"},"type":"s","scale":0.5},{"id":80,"iconCode":"img3483","x":690,"y":90,"width":40,"height":24,"src":"text/text01-html.svg","colorMapping":{},"textData":{"rows":8,"originalText":{"ops":[{"insert":"Body text. Body text."},{"insert":"\n"},{"insert":"Body text. Body text."},{"insert":"\n"},{"insert":"Body text. Body text."},{"insert":"\n"}]},"text":{"ops":[{"insert":"Exit\n"}]},"style":{"fontName":"Arial","fontSize":14,"fillColor":"#2D3134","lineHeight":1},"textType":"quill"},"type":"t","scale":0.5},{"id":81,"iconCode":"img3700","x":676,"y":126,"width":16,"height":32,"src":"office/fire-door-02.svg","originalScale":0.1,"colorMapping":{"#E5E5E5":"#E5E5E5","#CC291F":"#CC291F","#999999":"#999999"},"scale":0.5},{"id":82,"iconCode":"img3483","x":690,"y":114,"width":64,"height":24,"src":"text/text01-html.svg","colorMapping":{},"textData":{"rows":8,"originalText":{"ops":[{"insert":"Body text. Body text."},{"insert":"\n"},{"insert":"Body text. Body text."},{"insert":"\n"},{"insert":"Body text. Body text."},{"insert":"\n"}]},"text":{"ops":[{"insert":"Fire Exit\n"}]},"style":{"fontName":"Arial","fontSize":14,"fillColor":"#2D3134","lineHeight":1},"textType":"quill"},"type":"t","scale":0.5},{"id":84,"iconCode":"img412","x":676,"y":150,"width":16,"height":32,"src":"rooms/door-01.svg","originalScale":0.1,"flip":-1,"colorMapping":{"#BAA794":"#BAA794","#762C07":"#762C07","#825012":"#825012","#999999":"#999999"},"scale":0.5},{"id":85,"iconCode":"img3483","x":690,"y":138,"width":40,"height":24,"src":"text/text01-html.svg","colorMapping":{},"textData":{"rows":8,"originalText":{"ops":[{"insert":"Body text. Body text."},{"insert":"\n"},{"insert":"Body text. Body text."},{"insert":"\n"},{"insert":"Body text. Body text."},{"insert":"\n"}]},"text":{"ops":[{"insert":"Door\n"}]},"style":{"fontName":"Arial","fontSize":14,"fillColor":"#2D3134","lineHeight":1},"textType":"quill"},"type":"t","scale":0.5},{"id":86,"iconCode":"img432","x":676,"y":174,"width":16,"height":32,"src":"rooms/door-07.svg","scale":0.5,"originalScale":0.1,"flip":-1,"colorMapping":{"#BAA794":"#BAA794","#762C07":"#762C07","#825012":"#825012","#999999":"#999999"}},{"id":87,"iconCode":"img3483","x":690,"y":162,"width":104,"height":24,"src":"text/text01-html.svg","colorMapping":{},"textData":{"rows":8,"originalText":{"ops":[{"insert":"Body text. Body text."},{"insert":"\n"},{"insert":"Body text. Body text."},{"insert":"\n"},{"insert":"Body text. Body text."},{"insert":"\n"}]},"text":{"ops":[{"insert":"Objective Door\n"}]},"style":{"fontName":"Arial","fontSize":14,"fillColor":"#2D3134","lineHeight":1},"textType":"quill"},"type":"t","scale":0.5},{"id":88,"iconCode":"img992","x":674,"y":194,"width":2,"height":2,"src":"office/key.svg","scale":6,"originalScale":0.1,"colorMapping":{"#999999":"#539B00"}},{"id":89,"iconCode":"img3483","x":690,"y":186,"width":40,"height":24,"src":"text/text01-html.svg","colorMapping":{},"textData":{"rows":8,"originalText":{"ops":[{"insert":"Body text. Body text."},{"insert":"\n"},{"insert":"Body text. Body text."},{"insert":"\n"},{"insert":"Body text. Body text."},{"insert":"\n"}]},"text":{"ops":[{"insert":"Key \n"}]},"style":{"fontName":"Arial","fontSize":14,"fillColor":"#2D3134","lineHeight":1},"textType":"quill"},"type":"t","scale":0.5}],"fonts":{"googleFonts":[]}}